{
  "project_info": {
    "project_number": "185689851226",
    "project_id": "did-notification",
    "storage_bucket": "did-notification.firebasestorage.app"
  },
  "client": [
    {
      "client_info": {
        "mobilesdk_app_id": "1:185689851226:android:80aabf101f09b07a1e5f63",
        "android_client_info": {
          "package_name": "com.did.wallet"
        }
      },
      "oauth_client": [],
      "api_key": [
        {
          "current_key": "AIzaSyC7flXnDPvfLaUSzzSZibWrtoVFhgVEwls"
        }
      ],
      "services": {
        "appinvite_service": {
          "other_platform_oauth_client": []
        }
      }
    }
  ],
  "configuration_version": "1"
}